quantumlangchain/__init__.py
quantumlangchain/cli.py
quantumlangchain/licensing.py
quantumlangchain/agents/__init__.py
quantumlangchain/agents/entangled_agents.py
quantumlangchain/backends/__init__.py
quantumlangchain/backends/braket_backend.py
quantumlangchain/backends/pennylane_backend.py
quantumlangchain/backends/qiskit_backend.py
quantumlangchain/chains/__init__.py
quantumlangchain/chains/qlchain.py
quantumlangchain/cli/__init__.py
quantumlangchain/cli/license_cli.py
quantumlangchain/context/__init__.py
quantumlangchain/context/quantum_context_manager.py
quantumlangchain/core/__init__.py
quantumlangchain/core/base.py
quantumlangchain/memory/__init__.py
quantumlangchain/memory/quantum_memory.py
quantumlangchain/prompts/__init__.py
quantumlangchain/prompts/qprompt_chain.py
quantumlangchain/retrievers/__init__.py
quantumlangchain/retrievers/quantum_retriever.py
quantumlangchain/tools/__init__.py
quantumlangchain/tools/quantum_tool_executor.py
quantumlangchain/vectorstores/__init__.py
quantumlangchain/vectorstores/hybrid_chromadb.py
quantumlangchain/vectorstores/quantum_faiss.py
quantumlangchain-1.0.1.dist-info/METADATA
quantumlangchain-1.0.1.dist-info/WHEEL
quantumlangchain-1.0.1.dist-info/entry_points.txt
quantumlangchain-1.0.1.dist-info/top_level.txt
quantumlangchain-1.0.1.dist-info/RECORD
