Metadata-Version: 2.4
Name: quantumlangchain
Version: 1.0.1
Summary: LICENSED: A composable framework for quantum-inspired reasoning, entangled memory systems, and multi-agent cooperation
Author-email: Krishna Bajpai <bajpaikrishna715@gmail.com>
Maintainer-email: Krishna Bajpai <bajpaikrishna715@gmail.com>
License: Commercial License
Project-URL: Homepage, https://github.com/krish567366/Quantum-Langchain
Project-URL: Documentation, https://krish567366.github.io/Quantum-Langchain
Project-URL: Repository, https://github.com/krish567366/Quantum-Langchain
Project-URL: Issues, https://github.com/krish567366/Quantum-Langchain/issues
Keywords: quantum,langchain,ai,quantum-computing,agents,memory,entanglement,licensed,commercial
Classifier: Development Status :: 4 - Beta
Classifier: Intended Audience :: Developers
Classifier: Intended Audience :: Science/Research
Classifier: License :: Other/Proprietary License
Classifier: Operating System :: OS Independent
Classifier: Programming Language :: Python :: 3
Classifier: Programming Language :: Python :: 3.9
Classifier: Programming Language :: Python :: 3.10
Classifier: Programming Language :: Python :: 3.11
Classifier: Programming Language :: Python :: 3.12
Classifier: Topic :: Scientific/Engineering :: Artificial Intelligence
Classifier: Topic :: Scientific/Engineering :: Physics
Classifier: Topic :: Software Development :: Libraries :: Python Modules
Requires-Python: >=3.9
Requires-Dist: qiskit>=0.45.0
Requires-Dist: pennylane>=0.32.0
Requires-Dist: amazon-braket-sdk>=1.65.0
Requires-Dist: cirq>=1.2.0
Requires-Dist: torch>=2.0.0
Requires-Dist: transformers>=4.30.0
Requires-Dist: langchain>=0.1.0
Requires-Dist: langgraph>=0.0.40
Requires-Dist: chromadb>=0.4.0
Requires-Dist: faiss-cpu>=1.7.0
Requires-Dist: numpy>=1.24.0
Requires-Dist: pandas>=2.0.0
Requires-Dist: scipy>=1.10.0
Requires-Dist: networkx>=3.0
Requires-Dist: pydantic>=2.0.0
Requires-Dist: typing-extensions>=4.5.0
Requires-Dist: asyncio-pool>=0.6.0
Requires-Dist: matplotlib>=3.7.0
Requires-Dist: plotly>=5.15.0
Requires-Dist: jupyter>=1.0.0
Requires-Dist: rich>=13.0.0
Requires-Dist: tqdm>=4.65.0
Requires-Dist: quantummeta-license>=1.0.0
Provides-Extra: dev
Requires-Dist: pytest>=7.4.0; extra == "dev"
Requires-Dist: pytest-asyncio>=0.21.0; extra == "dev"
Requires-Dist: pytest-cov>=4.1.0; extra == "dev"
Requires-Dist: black>=23.0.0; extra == "dev"
Requires-Dist: ruff>=0.0.280; extra == "dev"
Requires-Dist: mypy>=1.5.0; extra == "dev"
Requires-Dist: pre-commit>=3.3.0; extra == "dev"
Provides-Extra: docs
Requires-Dist: mkdocs>=1.5.0; extra == "docs"
Requires-Dist: mkdocs-material>=9.1.0; extra == "docs"
Requires-Dist: mkdocstrings[python]>=0.22.0; extra == "docs"
Requires-Dist: mkdocs-jupyter>=0.24.0; extra == "docs"
Requires-Dist: mkdocs-mermaid2-plugin>=1.1.0; extra == "docs"
Provides-Extra: quantum-simulators
Requires-Dist: qulacs>=0.6.0; platform_system != "Windows" and extra == "quantum-simulators"
Requires-Dist: qulacs-cpu>=0.6.0; platform_system == "Windows" and extra == "quantum-simulators"
Provides-Extra: build-tools
Requires-Dist: cmake>=3.15.0; extra == "build-tools"
Requires-Dist: pybind11>=2.10.0; extra == "build-tools"
Provides-Extra: all
Requires-Dist: quantumlangchain[build-tools,dev,docs,quantum-simulators]; extra == "all"
Requires-Dist: pinecone-client>=2.2.0; extra == "all"
Requires-Dist: qdrant-client>=1.4.0; extra == "all"
Requires-Dist: autogen-agentchat>=0.2.0; extra == "all"
Requires-Dist: crewai>=0.1.0; extra == "all"
Requires-Dist: haystack-ai>=2.0.0; extra == "all"
